<?xml version="1.0" encoding="UTF-8"?>
<!DOCTYPE plist PUBLIC "-//Apple//DTD PLIST 1.0//EN" "http://www.apple.com/DTDs/PropertyList-1.0.dtd">
<plist version="1.0">
<array>
	<dict>
		<key>Actions</key>
		<array>
			<dict>
				<key>ActionColor</key>
				<string>Yellow</string>
				<key>ActionUID</key>
				<integer>15407994</integer>
				<key>MacroActionType</key>
				<string>Comment</string>
				<key>StyledText</key>
				<data>
							cnRmZAAAAAADAAAAAgAA
							AAcAAABUWFQucnRmAQAA
							AC5dAwAAKwAAAAEAAABV
							AwAAe1xydGYxXGFuc2lc
							YW5zaWNwZzEyNTJcY29j
							b2FydGYxNjcxXGNvY29h
							c3VicnRmNDAwCntcZm9u
							dHRibFxmMFxmc3dpc3Nc
							ZmNoYXJzZXQwIEhlbHZl
							dGljYTt9CntcY29sb3J0
							Ymw7XHJlZDI1NVxncmVl
							bjI1NVxibHVlMjU1O30K
							e1wqXGV4cGFuZGVkY29s
							b3J0Ymw7O30KXHBhcmRc
							dHg1NjBcdHgxMTIwXHR4
							MTY4MFx0eDIyNDBcdHgy
							ODAwXHR4MzM2MFx0eDM5
							MjBcdHg0NDgwXHR4NTA0
							MFx0eDU2MDBcdHg2MTYw
							XHR4NjcyMFxwYXJkaXJu
							YXR1cmFsXHBhcnRpZ2h0
							ZW5mYWN0b3IwCgpcZjBc
							ZnMyNCBcY2YwIE5hbWU6
							IFNwb3RsaWdodCBTZWFy
							Y2ggUHJvbXB0XApWZXJz
							aW9uOiAxLjBcClVwZGF0
							ZWQ6IDIwMTYvMDgvMTMg
							MTQ6MjIgUERUXApCeTog
							RGFuIFRob21hc1wKXApQ
							VVJQT1NFOlwKXApQcm92
							aWRlcyBhIHNlYXJjaGFi
							bGUgcGljayBsaXN0IHBy
							b21wdCwgc2ltaWxhciB0
							byBBcHBsZSdzIFNwb3Rs
							aWdodCBzZWFyY2guXApc
							ClVTQUdFOlwKXApZb3Ug
							c3VwcGx5IHRoZSBkYXRh
							IHRvIGJlIHNlYXJjaGVk
							LCBhbG9uZyB3aXRoIG9w
							dGlvbnMgc3BlY2lmeWlu
							ZyB0aGUgbGF5b3V0IG9m
							IHRoZSBkYXRhLCB3aGF0
							IGNhbiBiZSBzZWFyY2hl
							ZCwgYW5kIHdoYXQgdmFs
							dWUgdG8gcmV0dXJuLlwK
							XApMb29rIGF0IHRoZSBl
							eGFtcGxlIG1hY3JvcyBm
							b3IsIHdlbGwsIGV4YW1w
							bGVzLlwKXApGb3IgZnVs
							bCBkb2N1bWVudGF0aW9u
							LCBMYXVuY2ggdGhlIG1h
							Y3JvICJTcG90bGlnaHQg
							U2VhcmNoIFByb21wdCBE
							b2N1bWVudGF0aW9uIi4g
							QnV0IEkgcmVjb21tZW5k
							IGxvb2tpbmcgYXQgdGhl
							IGV4YW1wbGVzIGZpcnN0
							LlwKXApWRVJTSU9OIEhJ
							U1RPUlk6XAoxLjAgLSBJ
							bml0aWFsIHZlcnNpb24u
							fQEAAAAjAAAAAQAAAAcA
							AABUWFQucnRmEAAAAAOB
							sFy2AQAAAAAAAAAAAAA=
							</data>
				<key>Title</key>
				<string>Spotlight Search Prompt v1.0</string>
			</dict>
			<dict>
				<key>ActionName</key>
				<string>Empty Template for specifying all the available options.</string>
				<key>ActionUID</key>
				<integer>15407995</integer>
				<key>IsActive</key>
				<false/>
				<key>MacroActionType</key>
				<string>SetVariableToText</string>
				<key>Text</key>
				<string>title:
dataType:

jsonDisplayField:
jsonReturnField:
jsonAdditionalSearchFields:
jsonStatusLineFields:
jsonStatusLineTemplate:
jsonStatusLineFunction:

placeholder:
cancelMacroIfCancelClicked:
helpMacroUUID:
customButtonText:
customButtonSubmitResultButton:
customButtonTriggerMacroUUID:
customButtonEnabledWithoutSelection:

customPromptWidth:
customPickListSize:
saveWindowPositionVariableName:
</string>
				<key>Variable</key>
				<string>sspOptions</string>
			</dict>
			<dict>
				<key>ActionColor</key>
				<string>Green</string>
				<key>ActionName</key>
				<string>Verify and/or set DND__sspResourcesPackagePath</string>
				<key>ActionUID</key>
				<integer>15407996</integer>
				<key>Actions</key>
				<array>
					<dict>
						<key>ActionColor</key>
						<string>Orange</string>
						<key>ActionName</key>
						<string>Verify and/or set DND__sspResourcesPackagePath, loop until valid or canceled</string>
						<key>ActionUID</key>
						<integer>15407997</integer>
						<key>Actions</key>
						<array>
							<dict>
								<key>ActionName</key>
								<string>Tell the user we need them to locate the resources package for us.</string>
								<key>ActionUID</key>
								<integer>15407998</integer>
								<key>Buttons</key>
								<array>
									<dict>
										<key>Button</key>
										<string>OK</string>
									</dict>
									<dict>
										<key>Button</key>
										<string>Cancel</string>
										<key>Cancel</key>
										<true/>
									</dict>
								</array>
								<key>IsDisclosed</key>
								<false/>
								<key>MacroActionType</key>
								<string>PromptForUserInput</string>
								<key>Prompt</key>
								<string>You need to specify the location of the Resources package "Spotlight Search Prompt Resources.pkg".

Please click "OK", and locate the Resources package.</string>
								<key>TimeOutAbortsMacro</key>
								<true/>
								<key>Title</key>
								<string>Spotlight Search</string>
								<key>Variables</key>
								<array/>
							</dict>
							<dict>
								<key>ActionName</key>
								<string>Have the user pick the resources package</string>
								<key>ActionUID</key>
								<integer>15407999</integer>
								<key>DisplayKind</key>
								<string>Variable</string>
								<key>HonourFailureSettings</key>
								<true/>
								<key>IncludeStdErr</key>
								<true/>
								<key>IncludedVariables</key>
								<array>
									<string>9999</string>
								</array>
								<key>IsDisclosed</key>
								<false/>
								<key>MacroActionType</key>
								<string>ExecuteAppleScript</string>
								<key>NotifyOnFailure</key>
								<false/>
								<key>Path</key>
								<string></string>
								<key>StopOnFailure</key>
								<false/>
								<key>Text</key>
								<string>tell application (path to frontmost application as text)	set dir to POSIX path of (choose file with prompt "Please locate the file 'Spotlight Search Prompt Resources.pkg'")end tell</string>
								<key>TimeOutAbortsMacro</key>
								<true/>
								<key>TrimResults</key>
								<true/>
								<key>TrimResultsNew</key>
								<true/>
								<key>UseText</key>
								<true/>
								<key>Variable</key>
								<string>DND__sspResourcesPackagePath</string>
							</dict>
							<dict>
								<key>Action</key>
								<string>CaseSensitiveRegEx</string>
								<key>ActionName</key>
								<string>Remove trailing backslash, which we get because a package file is basically a folder.</string>
								<key>ActionUID</key>
								<integer>15408000</integer>
								<key>IsDisclosed</key>
								<false/>
								<key>MacroActionType</key>
								<string>SearchReplace</string>
								<key>Replace</key>
								<string></string>
								<key>Search</key>
								<string>(\/)$</string>
								<key>Source</key>
								<string>Variable</string>
								<key>Variable</key>
								<string>DND__sspResourcesPackagePath</string>
								<key>Which</key>
								<string>All</string>
							</dict>
						</array>
						<key>Conditions</key>
						<dict>
							<key>ConditionList</key>
							<array>
								<dict>
									<key>ConditionType</key>
									<string>Variable</string>
									<key>Variable</key>
									<string>DND__sspResourcesPackagePath</string>
									<key>VariableConditionType</key>
									<string>IsEmpty</string>
									<key>VariableValue</key>
									<string>value</string>
								</dict>
								<dict>
									<key>ConditionType</key>
									<string>Path</string>
									<key>Path</key>
									<string>%Variable%DND__sspResourcesPackagePath%/Spotlight Search Prompt.html</string>
									<key>PathConditionType</key>
									<string>FileDoesNotExists</string>
								</dict>
							</array>
							<key>ConditionListMatch</key>
							<string>Any</string>
						</dict>
						<key>IsDisclosed</key>
						<false/>
						<key>MacroActionType</key>
						<string>While</string>
						<key>TimeOutAbortsMacro</key>
						<true/>
					</dict>
					<dict>
						<key>ActionName</key>
						<string>Jump out of this macro, if "verify only" is true.</string>
						<key>ActionUID</key>
						<integer>15408001</integer>
						<key>Conditions</key>
						<dict>
							<key>ConditionList</key>
							<array>
								<dict>
									<key>ConditionType</key>
									<string>Text</string>
									<key>Text</key>
									<string>%TriggerValue%</string>
									<key>TextConditionType</key>
									<string>Contains</string>
									<key>TextValue</key>
									<string>verify only</string>
								</dict>
							</array>
							<key>ConditionListMatch</key>
							<string>All</string>
						</dict>
						<key>ElseActionListDisclosed</key>
						<false/>
						<key>ElseActions</key>
						<array/>
						<key>IsDisclosed</key>
						<false/>
						<key>MacroActionType</key>
						<string>IfThenElse</string>
						<key>ThenActions</key>
						<array>
							<dict>
								<key>Action</key>
								<string>CancelJustThisMacro</string>
								<key>ActionUID</key>
								<integer>15408002</integer>
								<key>IsDisclosed</key>
								<false/>
								<key>MacroActionType</key>
								<string>Cancel</string>
							</dict>
						</array>
						<key>TimeOutAbortsMacro</key>
						<true/>
					</dict>
				</array>
				<key>IsDisclosed</key>
				<false/>
				<key>MacroActionType</key>
				<string>Group</string>
				<key>TimeOutAbortsMacro</key>
				<true/>
			</dict>
			<dict>
				<key>ActionColor</key>
				<string>Teal</string>
				<key>ActionName</key>
				<string>Show Custom HTML Prompt, abort if error</string>
				<key>ActionUID</key>
				<integer>15408003</integer>
				<key>Actions</key>
				<array>
					<dict>
						<key>ActionUID</key>
						<integer>15408004</integer>
						<key>IsDisclosed</key>
						<false/>
						<key>MacroActionType</key>
						<string>SetVariableToText</string>
						<key>Text</key>
						<string></string>
						<key>Variable</key>
						<string>sspResult</string>
					</dict>
					<dict>
						<key>ActionColor</key>
						<string>Magenta</string>
						<key>ActionName</key>
						<string>Setup/Calculate Window Width, Height, PickListSize</string>
						<key>ActionUID</key>
						<integer>15408005</integer>
						<key>Actions</key>
						<array>
							<dict>
								<key>ActionName</key>
								<string>Get either Custom or Default sspWindowWidth</string>
								<key>ActionUID</key>
								<integer>15408006</integer>
								<key>Conditions</key>
								<dict>
									<key>ConditionList</key>
									<array>
										<dict>
											<key>ConditionType</key>
											<string>Variable</string>
											<key>Variable</key>
											<string>sspOptions</string>
											<key>VariableConditionType</key>
											<string>Matches</string>
											<key>VariableValue</key>
											<string>(?m)^customPromptWidth:\s*(\d+)</string>
										</dict>
									</array>
									<key>ConditionListMatch</key>
									<string>All</string>
								</dict>
								<key>ElseActions</key>
								<array>
									<dict>
										<key>ActionName</key>
										<string>Set Variable ‘sspWindowWidth’ (default 400)</string>
										<key>ActionUID</key>
										<integer>15408008</integer>
										<key>IsDisclosed</key>
										<false/>
										<key>MacroActionType</key>
										<string>SetVariableToCalculation</string>
										<key>Text</key>
										<string>400</string>
										<key>UseFormat</key>
										<false/>
										<key>Variable</key>
										<string>sspWindowWidth</string>
									</dict>
								</array>
								<key>IsDisclosed</key>
								<false/>
								<key>MacroActionType</key>
								<string>IfThenElse</string>
								<key>ThenActions</key>
								<array>
									<dict>
										<key>Action</key>
										<string>IgnoreCaseRegEx</string>
										<key>ActionName</key>
										<string>Get custom sspWindowWidth</string>
										<key>ActionUID</key>
										<integer>15408007</integer>
										<key>Captures</key>
										<array>
											<string></string>
											<string>sspWindowWidth</string>
										</array>
										<key>IsDisclosed</key>
										<false/>
										<key>MacroActionType</key>
										<string>SearchRegEx</string>
										<key>Search</key>
										<string>(?m)^customPromptWidth:\s*(\d+)</string>
										<key>Source</key>
										<string>Variable</string>
										<key>Variable</key>
										<string>sspOptions</string>
									</dict>
								</array>
								<key>TimeOutAbortsMacro</key>
								<true/>
							</dict>
							<dict>
								<key>ActionName</key>
								<string>Get either Custom or Default sspPickListSize</string>
								<key>ActionUID</key>
								<integer>15408009</integer>
								<key>Conditions</key>
								<dict>
									<key>ConditionList</key>
									<array>
										<dict>
											<key>ConditionType</key>
											<string>Variable</string>
											<key>Variable</key>
											<string>sspOptions</string>
											<key>VariableConditionType</key>
											<string>Matches</string>
											<key>VariableValue</key>
											<string>(?m)^customPickListSize:\s*(\d+)</string>
										</dict>
									</array>
									<key>ConditionListMatch</key>
									<string>All</string>
								</dict>
								<key>ElseActions</key>
								<array>
									<dict>
										<key>ActionName</key>
										<string>Default sspPickListSize (15)</string>
										<key>ActionUID</key>
										<integer>15408011</integer>
										<key>IsDisclosed</key>
										<false/>
										<key>MacroActionType</key>
										<string>SetVariableToCalculation</string>
										<key>Text</key>
										<string>15</string>
										<key>UseFormat</key>
										<false/>
										<key>Variable</key>
										<string>sspPickListSize</string>
									</dict>
								</array>
								<key>IsDisclosed</key>
								<false/>
								<key>MacroActionType</key>
								<string>IfThenElse</string>
								<key>ThenActions</key>
								<array>
									<dict>
										<key>Action</key>
										<string>IgnoreCaseRegEx</string>
										<key>ActionName</key>
										<string>Get custom sspPickListSize</string>
										<key>ActionUID</key>
										<integer>15408010</integer>
										<key>Captures</key>
										<array>
											<string></string>
											<string>sspPickListSize</string>
										</array>
										<key>IsDisclosed</key>
										<false/>
										<key>MacroActionType</key>
										<string>SearchRegEx</string>
										<key>Search</key>
										<string>(?m)^customPickListSize:\s*(\d+)</string>
										<key>Source</key>
										<string>Variable</string>
										<key>Variable</key>
										<string>sspOptions</string>
									</dict>
								</array>
								<key>TimeOutAbortsMacro</key>
								<true/>
							</dict>
							<dict>
								<key>ActionColor</key>
								<string>Yellow</string>
								<key>ActionUID</key>
								<integer>15408012</integer>
								<key>MacroActionType</key>
								<string>Comment</string>
								<key>StyledText</key>
								<data>
								cnRmZAAAAAAD
								AAAAAgAAAAcA
								AABUWFQucnRm
								AQAAAC68AgAA
								KwAAAAEAAAC0
								AgAAe1xydGYx
								XGFuc2lcYW5z
								aWNwZzEyNTJc
								Y29jb2FydGYx
								NjcxXGNvY29h
								c3VicnRmNDAw
								CntcZm9udHRi
								bFxmMFxmc3dp
								c3NcZmNoYXJz
								ZXQwIEhlbHZl
								dGljYTt9Cntc
								Y29sb3J0Ymw7
								XHJlZDI1NVxn
								cmVlbjI1NVxi
								bHVlMjU1O30K
								e1wqXGV4cGFu
								ZGVkY29sb3J0
								Ymw7O30KXHBh
								cmRcdHg1NjBc
								dHgxMTIwXHR4
								MTY4MFx0eDIy
								NDBcdHgyODAw
								XHR4MzM2MFx0
								eDM5MjBcdHg0
								NDgwXHR4NTA0
								MFx0eDU2MDBc
								dHg2MTYwXHR4
								NjcyMFxwYXJk
								aXJuYXR1cmFs
								XHBhcnRpZ2h0
								ZW5mYWN0b3Iw
								CgpcZjBcZnMy
								NCBcY2YwIEl0
								J3MgcXVpdGUg
								cG9zc2libGUg
								dGhhdCB0aGUg
								aGVpZ2h0IG9m
								IG9uZSBQaWNr
								TGlzdCBsaW5l
								IGlzIGRpZmZl
								cmVudCBmcm9t
								IG1pbmUsIG9y
								IHBlcmhhcHMg
								c29tZSBvdGhl
								ciBtZXRyaWMg
								aXMgZGlmZmVy
								ZW50LiBJZiB0
								aGF0IGhhcHBl
								bnMsIHlvdSBt
								aWdodCBzdGFy
								dCBzZWVpbmcg
								YW4gZXh0cmEg
								dmVydGljYWwg
								c2Nyb2xsIGJh
								ci5cClwKSWYg
								dGhhdCBoYXBw
								ZW5zLCB0cnkg
								Y2hhbmdpbmcg
								dGhlICJQaWNr
								TGlzdEl0ZW0g
								aGVpZ2h0IiAo
								ZGVmYXVsdCAx
								NyksIGFuZC9v
								ciB0aGUgIlBy
								b21wdCBIZWln
								aHQgd2l0aG91
								dCB0aGUgUGlj
								ayBMaXN0IiAo
								ZGVmYXVsdCAx
								NDkpLlwKXApS
								dW4gdGhlICJT
								cG90bGlnaHQg
								U2VhcmNoIFBy
								b21wdCBEb2N1
								bWVudGF0aW9u
								IiBmb3IgbW9y
								ZSBkZXRhaWxz
								Ln0BAAAAIwAA
								AAEAAAAHAAAA
								VFhULnJ0ZhAA
								AAADgbBctgEA
								AAAAAAAAAAAA
											</data>
								<key>Title</key>
								<string>Adjusting the height calculations for the prompt</string>
							</dict>
							<dict>
								<key>ActionColor</key>
								<string>Green</string>
								<key>ActionName</key>
								<string>Calculate Window Height: 17=PickListItem height, 149=Prompt Height without PickList</string>
								<key>ActionUID</key>
								<integer>15408013</integer>
								<key>MacroActionType</key>
								<string>SetVariableToCalculation</string>
								<key>Text</key>
								<string>(sspPickListSize * 17.1) + 149</string>
								<key>UseFormat</key>
								<false/>
								<key>Variable</key>
								<string>sspWindowHeight</string>
							</dict>
						</array>
						<key>MacroActionType</key>
						<string>Group</string>
						<key>TimeOutAbortsMacro</key>
						<true/>
					</dict>
					<dict>
						<key>ActionUID</key>
						<integer>15408014</integer>
						<key>Floating</key>
						<true/>
						<key>IsDisclosed</key>
						<false/>
						<key>MacroActionType</key>
						<string>CustomPrompt</string>
						<key>Path</key>
						<string>%Variable%DND__sspResourcesPackagePath%/Spotlight Search Prompt.html</string>
						<key>TimeOutAbortsMacro</key>
						<true/>
						<key>UseText</key>
						<false/>
					</dict>
					<dict>
						<key>ActionColor</key>
						<string>Red</string>
						<key>ActionName</key>
						<string>Cancel if error</string>
						<key>ActionUID</key>
						<integer>15408015</integer>
						<key>Conditions</key>
						<dict>
							<key>ConditionList</key>
							<array>
								<dict>
									<key>ConditionType</key>
									<string>Variable</string>
									<key>Variable</key>
									<string>HTML Result Button</string>
									<key>VariableConditionType</key>
									<string>Is</string>
									<key>VariableValue</key>
									<string>Error</string>
								</dict>
							</array>
							<key>ConditionListMatch</key>
							<string>All</string>
						</dict>
						<key>ElseActionListDisclosed</key>
						<false/>
						<key>ElseActions</key>
						<array/>
						<key>IsDisclosed</key>
						<false/>
						<key>MacroActionType</key>
						<string>IfThenElse</string>
						<key>ThenActions</key>
						<array>
							<dict>
								<key>ActionUID</key>
								<integer>15408016</integer>
								<key>DeviceID</key>
								<string>SOUNDEFFECTS</string>
								<key>IsDisclosed</key>
								<false/>
								<key>MacroActionType</key>
								<string>PlaySound</string>
								<key>Path</key>
								<string>/System/Library/Sounds/Basso.aiff</string>
								<key>TimeOutAbortsMacro</key>
								<true/>
							</dict>
							<dict>
								<key>ActionName</key>
								<string>Notify error '%Variable%sspResult%'</string>
								<key>ActionUID</key>
								<integer>15408017</integer>
								<key>Buttons</key>
								<array>
									<dict>
										<key>Button</key>
										<string>OK</string>
										<key>Cancel</key>
										<true/>
									</dict>
								</array>
								<key>IsDisclosed</key>
								<false/>
								<key>MacroActionType</key>
								<string>PromptForUserInput</string>
								<key>Prompt</key>
								<string>%Variable%sspResult%</string>
								<key>TimeOutAbortsMacro</key>
								<true/>
								<key>Title</key>
								<string>%ExecutingThisMacro%</string>
								<key>Variables</key>
								<array/>
							</dict>
							<dict>
								<key>Action</key>
								<string>CancelThisMacro</string>
								<key>ActionUID</key>
								<integer>15408018</integer>
								<key>IsDisclosed</key>
								<false/>
								<key>MacroActionType</key>
								<string>Cancel</string>
							</dict>
						</array>
						<key>TimeOutAbortsMacro</key>
						<true/>
					</dict>
					<dict>
						<key>ActionColor</key>
						<string>Green</string>
						<key>ActionName</key>
						<string>Store the HTML Result Button in sspResultButton</string>
						<key>ActionUID</key>
						<integer>15408019</integer>
						<key>Conditions</key>
						<dict>
							<key>ConditionList</key>
							<array>
								<dict>
									<key>ConditionType</key>
									<string>Variable</string>
									<key>Variable</key>
									<string>HTML Result Button</string>
									<key>VariableConditionType</key>
									<string>IsEmpty</string>
									<key>VariableValue</key>
									<string>value</string>
								</dict>
							</array>
							<key>ConditionListMatch</key>
							<string>All</string>
						</dict>
						<key>ElseActions</key>
						<array>
							<dict>
								<key>ActionUID</key>
								<integer>15408021</integer>
								<key>MacroActionType</key>
								<string>SetVariableToText</string>
								<key>Text</key>
								<string>%Variable%HTML Result Button%</string>
								<key>Variable</key>
								<string>sspResultButton</string>
							</dict>
						</array>
						<key>IsDisclosed</key>
						<false/>
						<key>MacroActionType</key>
						<string>IfThenElse</string>
						<key>ThenActions</key>
						<array>
							<dict>
								<key>ActionUID</key>
								<integer>15408020</integer>
								<key>MacroActionType</key>
								<string>SetVariableToText</string>
								<key>Text</key>
								<string>Cancel</string>
								<key>Variable</key>
								<string>sspResultButton</string>
							</dict>
						</array>
						<key>TimeOutAbortsMacro</key>
						<true/>
					</dict>
				</array>
				<key>MacroActionType</key>
				<string>Group</string>
				<key>TimeOutAbortsMacro</key>
				<true/>
			</dict>
			<dict>
				<key>ActionColor</key>
				<string>Yellow</string>
				<key>ActionName</key>
				<string>Cleanup Variables</string>
				<key>ActionUID</key>
				<integer>15408022</integer>
				<key>Actions</key>
				<array>
					<dict>
						<key>ActionUID</key>
						<integer>15408023</integer>
						<key>IsDisclosed</key>
						<false/>
						<key>MacroActionType</key>
						<string>SetVariableToText</string>
						<key>Text</key>
						<string>%Delete%</string>
						<key>Variable</key>
						<string>sspOptions</string>
					</dict>
					<dict>
						<key>ActionUID</key>
						<integer>15408024</integer>
						<key>IsDisclosed</key>
						<false/>
						<key>MacroActionType</key>
						<string>SetVariableToText</string>
						<key>Text</key>
						<string>%Delete%</string>
						<key>Variable</key>
						<string>sspData</string>
					</dict>
					<dict>
						<key>ActionUID</key>
						<integer>15408025</integer>
						<key>IsDisclosed</key>
						<false/>
						<key>MacroActionType</key>
						<string>SetVariableToText</string>
						<key>Text</key>
						<string>%Delete%</string>
						<key>Variable</key>
						<string>sspPickListSize</string>
					</dict>
					<dict>
						<key>ActionUID</key>
						<integer>15408026</integer>
						<key>IsDisclosed</key>
						<false/>
						<key>MacroActionType</key>
						<string>SetVariableToText</string>
						<key>Text</key>
						<string>%Delete%</string>
						<key>Variable</key>
						<string>sspWindowWidth</string>
					</dict>
					<dict>
						<key>ActionUID</key>
						<integer>15408027</integer>
						<key>IsDisclosed</key>
						<false/>
						<key>MacroActionType</key>
						<string>SetVariableToText</string>
						<key>Text</key>
						<string>%Delete%</string>
						<key>Variable</key>
						<string>sspWindowHeight</string>
					</dict>
				</array>
				<key>IsDisclosed</key>
				<false/>
				<key>MacroActionType</key>
				<string>Group</string>
				<key>TimeOutAbortsMacro</key>
				<true/>
			</dict>
			<dict>
				<key>ActionColor</key>
				<string>Red</string>
				<key>ActionName</key>
				<string>Cancel the macro if the user cancels the prompt, if needed</string>
				<key>ActionUID</key>
				<integer>15408028</integer>
				<key>Conditions</key>
				<dict>
					<key>ConditionList</key>
					<array>
						<dict>
							<key>ConditionType</key>
							<string>Calculation</string>
							<key>Text</key>
							<string>sspCancelMacroIfCancelClicked</string>
						</dict>
					</array>
					<key>ConditionListMatch</key>
					<string>All</string>
				</dict>
				<key>ElseActions</key>
				<array>
					<dict>
						<key>ActionColor</key>
						<string>Yellow</string>
						<key>ActionUID</key>
						<integer>15408032</integer>
						<key>IsDisclosed</key>
						<false/>
						<key>MacroActionType</key>
						<string>SetVariableToText</string>
						<key>Text</key>
						<string>%Delete%</string>
						<key>Variable</key>
						<string>sspCancelMacroIfCancelClicked</string>
					</dict>
				</array>
				<key>IsDisclosed</key>
				<false/>
				<key>MacroActionType</key>
				<string>IfThenElse</string>
				<key>ThenActions</key>
				<array>
					<dict>
						<key>ActionName</key>
						<string>Cancel the macro if the user cancels the prompt.</string>
						<key>ActionUID</key>
						<integer>15408029</integer>
						<key>Conditions</key>
						<dict>
							<key>ConditionList</key>
							<array>
								<dict>
									<key>ConditionType</key>
									<string>Variable</string>
									<key>Variable</key>
									<string>HTML Result Button</string>
									<key>VariableConditionType</key>
									<string>Is</string>
									<key>VariableValue</key>
									<string>Cancel</string>
								</dict>
								<dict>
									<key>ConditionType</key>
									<string>Variable</string>
									<key>Variable</key>
									<string>sspResult</string>
									<key>VariableConditionType</key>
									<string>IsEmpty</string>
									<key>VariableValue</key>
									<string>value</string>
								</dict>
							</array>
							<key>ConditionListMatch</key>
							<string>Any</string>
						</dict>
						<key>ElseActionListDisclosed</key>
						<false/>
						<key>ElseActions</key>
						<array/>
						<key>IsDisclosed</key>
						<false/>
						<key>MacroActionType</key>
						<string>IfThenElse</string>
						<key>ThenActions</key>
						<array>
							<dict>
								<key>ActionColor</key>
								<string>Yellow</string>
								<key>ActionUID</key>
								<integer>15408030</integer>
								<key>IsDisclosed</key>
								<false/>
								<key>MacroActionType</key>
								<string>SetVariableToText</string>
								<key>Text</key>
								<string>%Delete%</string>
								<key>Variable</key>
								<string>sspCancelMacroIfCancelClicked</string>
							</dict>
							<dict>
								<key>Action</key>
								<string>CancelThisMacro</string>
								<key>ActionColor</key>
								<string>Red</string>
								<key>ActionUID</key>
								<integer>15408031</integer>
								<key>IsDisclosed</key>
								<false/>
								<key>MacroActionType</key>
								<string>Cancel</string>
							</dict>
						</array>
						<key>TimeOutAbortsMacro</key>
						<true/>
					</dict>
				</array>
				<key>TimeOutAbortsMacro</key>
				<true/>
			</dict>
		</array>
		<key>CreationDate</key>
		<real>492020921.240987</real>
		<key>CustomIconData</key>
		<data>
					TU0AKgAAFgqAACBQOCQWDQeEQmFQuGQ2HQ+I
					RGJROKRWLReMRYAgGBRsBAQCgeOgIAgMDAUA
					RuNv8AgSUxyCv9/gCWP9+TSZP9+vt9wJ/v5/
					Px9PqfTOaP6M0mlUumU2KxsBgUEAsBAMDgkF
					BQUi+TAsHAgHh4RR8EAmrA8J1ABwSZP5+v59
					PF4W58vd8PBwtx+vp6PJ6u1tNGgvh73t7PSi
					07FYvGY2CSW1gEBR8C17JSABggHBEBgQEgsG
					BQT1wDAyvhCxR+rgQDhG05K1wO2v293Kg3V8
					PG83u+vN14F+vx7vV+vd4O+fvx98p6vKj0id
					TfHdPqdWR1YEhILawIBMIiYnF0DAoKhkGhYX
					jaoggFWXWZLLgOoyrYS2OTCYgCgTaczZ+H8f
					b9n8wh9n0nZ8MOdhqmafR7HYc53G0V5Qn4fJ
					4HafK/nQmjaOtD0PomqACgUBjJAMA7NA0EIC
					uyCwJhMKDxAWCgMAcCwXBuqMUJOmaNoEAYBH
					6lKBslHqCo4oyUqNJJ9n6taZIEfSegAnZ8nw
					eZ2GvBkHHQdhsQmfZ7ncdUrnGbydH0fLDHmx
					MQTdNwBRGBgJA+IAnAMBYLg4CYRvCAywAkBg
					IASBz5PkAyQAQ+iqoO/CaJ8AKkSIAJ/gEjtH
					oPJKBuCnCcybAraNoeh6HueR9HweR3wiWhSH
					0ep0nIdpwF8WEAHrNk31yxjJtZQSTAa7oRCQ
					KoDgYDAOgqEglC4qQGgeBQEqQyaZgJH1HAFJ
					MkPyfyWUkjtKUtIdHSI/KdUpJMhW6lgAHsfN
					LH2fC+nYbhcFMfJ5nQcd5lsVC91TCp6HigSg
					V1gqKpMzYLhULA1NLY4KA8HglJCrwGAaBIGM
					myUhpejqcvu/SZ2xdZ+0qnGB5LRqC0ZjoAAH
					SKX5FJCZ5pmckpZSluH8eZ7OGfcMnkdhumEW
					h8npfJ1GwVRL38d+DaehcRAUBoCAQCLyhcMQ
					6AOBoMg8CYOBiIACz/aCUZxmslp9tajKC2lu
					J+nmfp+n7aOUmNrR+AjOpVOICpDvrOgIl1HW
					5H0lJImSOHxIQAwLBB1m+Zpf3uc5xnQapQkY
					fh8HedadnqxCj6hg04gWBoJA8IgqWKDAPAwF
					opjJP4HgkBoFRZjVzvxHuSp/SR7n8jbguCeh
					2nScKhOaex3GgY3i1Mep2HMmTgpUAqN8HEYJ
					gqqPTgWCYXByAjSgcBIHgwEG9qiBQDI5aaBX
					DnEhpm/Z/noex9nsfR7nid46BrCxFA0YdA4l
					ZC4FSrY5zpEQPZAKwhq4JwqBma4BoD4GQThE
					Csn8rwB3sP0ZaT8gRQigQlH8PUe49B4D8KEl
					cdY4xuFChUmJ5xOy+phemfqFhLD5kffI1YCr
					pnbgVBg+M0oEAFFhBISAq4DjQASMmZMqx9E2
					pGHyPomapx7L4G2L4Vq9xzDhHUNlpZtR3HJS
					nAwxhJVerHTwscDwNw9iYAQAwCwGwIgPYwkB
					jbHFNj8JmW8mQ8x6v6f4hcdY2RTCRQaOoco9
					B1jUGYYMepQB8j5Jwzpu5j3DrfM6S+KIBwDl
					kAUAoCYKAZHjjuBcFAXA3gGASBACgDQGLFj5
					GxcZ+luSCH+PAeTRmjDrjCMsQwbFXQFjAOAm
					Um41FLRMVcCQJQXmlgsCEGwdxJAHfABh27Mk
					lqWSgAAfQ/C3nBOUO8dsL3+PHS8KQR6YZhD0
					HcNcZ6aB8GOmeAuaIL0WAVA0BUE4Xg4njAmB
					gCIFALAfcE2RwZJFHMlKARweg+CSIZeOOAZQ
					jg4qujCX8awzifqnmaUw1jV3YBrEHHUDIHwM
					AiBgD6H7uDHsDSgbQmQ8h5zAHrMIcIyxEhuf
					0vmeA5I0E6kubI6pUADvuMoiwCwHkRgYA4B4
					GgdBHzan8A98yhWXqWSCdAgRbwCACKEXUdI4
					hpjHXiOccI5xoCSDwhVMdIyMxsaqjQDoNA7i
					TpUB+fwIAVEgJCthca6UqQsH4O0dQ6xxLxgK
					OUZwhQ1TwHKmtNrpDYJ4AYZ6fzYQ8CUjqscC
					QFwLghcGSAkhby2MurITwfQ7B0DlG3WscI4h
					lCEDQ5xB6HDpV0IdZkA52jxgYA+B8HghRSFT
					T0A0BYAADMaUuyEgQ9x7rVLq54cgzxLB7VdW
					w3zzidIIJ8t63xKSSHYNCC0HCeKVgdBkG0Q8
					0ALAJATIAkhsi2lGHoPUAC8B6jqHIOAYwfAv
					XdHC/wdyGydJCvKQiB17AQXsA+CIHIghQ1YA
					1KUfalSYJGP2ABUc4h8oOcsMsRAbUGjoHClc
					cI2W4lEwao0yixQOgluGB4DwNg8iWAOeQDQD
					AFgBAK7olbdLpj4yGhmYQ3RjiADDgYfQ8xyp
					nJtGnGJBCPokAcBsHoTptUrA4CsLgc3aATAO
					AQt7hyfpAhYgUdg6hvjVtoOUaAjQ426HO3GT
					GVyGmSoYAegoGgXhwEYsWlYFQLgkBeSBE5VV
					JFGHwPtSypx4juHKNYVIkkM1sHiOSLxQYt58
					ZWZUzYHgkBby+B8DQKAoBmROA0CIBQCQiIIP
					4yZyn+DoHINMZGmxwjoGoJQO9ch1aiIoSZq4
					GQVhoEJqkCoHQYg9bIexveDCBj50liIeY8Bz
					jZFoJ/Xw7hwi0FAgBgOxiBkmlkBcEoYQ96pA
					yCAGoRtp3NAHrRKI+kgKnHlpaMmmh66cHLp8
					fmod0ERyyaYDIPMvAKzACrMeZQDAGUkfg6SB
					R7j2gKM4Xuvh0DZE4IIvY8B18HZcAbZIKAz7
					NAXcQC4HQYA9iYAolr9iOJpSAvAeI7BwjWE8
					IRBtbGjjKF2W44fJiIElPYA0CoMggHjpWB4F
					oZhAywAgBXiaPVKIcrCmke9sRqDGQziqAAlQ
					8lCHfsXg75KC7KDoJSbVxALAZBEC0qLgABc2
					ABCjfY9x266GgIzFA9q2D3HmN0aWeukEPz8i
					cBgHgU9QA+B4GIeRMFXAmBkBYCutM0wZm0fQ
					6R2DjGv2PX40BD25HyO0c/JjWeZA0CoO+POW
					1+pWCszrZDJd6hQZNBvrBxjREQGnoOKx5jiG
					sTJAvi/GRMAYBzG3DgP8wD0JzHoFANMXW+/V
					SU5h9DqHcOQbnphzjPEMGNCtu+16AAyBgFgd
					xNY9uJogD4J/cvuU6QNdpG3+IPHGGgESDIxS
					HCaMHCG2OSxg+YaiJabIAUfSRYuIA+BmD8FC
					lg+wAS4o1sw6AAMmbsH0wSHE/G40HCHKGqEQ
					/QHy/U3QKs8y2UDqEu/kA+AotKsC0YZsKMfy
					JSnWcsGeEUDQ1zAIHoHCGuxfAUIYweAWA2BJ
					AguKBiD0E7AsA1AwJ+vuUfA6J2H07+HCG0xG
					xUHMGsESDKQq9Y5M2QAuAwBMDYEXBiAkAyBS
					BscGRQZybgIEHyH498c6HUHOGuEuD1CAHqHe
					GoGKJ+LrCMaiAElgiSBWBslguIA0BWDSEWT+
					O0AQWqZaeEhGhawSGwGbC61+GyEmDkL2HcHT
					DKAKAgAsAsBK5WuG9sBc5kKkASLarAnEH698
					QsHYHSGwFA6A6+HCHmHcGWF2vCv5EMISMk6W
					AkBiCFEapYBQDGD+T+6uUQJglyhYLqmEGkGL
					AGHUG4EyD0L27S5MI+1gAiA0CeDPGaAsBECG
					C0fIK8WqYIU3A4rIQaHozgGKFjCA/CFSEcKC
					HkHbGMISI+AcAkAkA4CoDdHUBCB8CnAaAbCq
					1qXWQKOaHUG8F8FVH2HKFeEqKCHmac4OKqAW
					AeAeAuCMC3HUBGCYDMNYWAyHHkYGMkSCXgHs
					sYGiGFCAHaHCE+EAJ25IZRIEOvFOAqAmA+DA
					D5GaAq8oCGPWAUNiIKQChGXuHgHUG6FuE9CA
					HgHQFuFCLcHqYE4OI2JCa4BKBiKlEcBMDaEg
					KkoKKwojGrHoLcW5GALqf4HUHGtkECCyKEHU
					HEN5JBJhLCNgjqfIqeA2BQEEFWlgAuA8AYAe
					KuI+JId0nCZ6KQXhFI26EsDkXgxUXiG0GapC
					nu5NAYKuA2BKKkAuA+AuBODqEyT+Amx+yCio
					Y2WwUkhUSiHwemHOG4EUDGZ+eQf4HKG4JomY
					3QjYbIqeJDNSgwD2FGT+AqA2dOcUvvMmSgHm
					HoLcXgQeHQG0EeDSXhOAHsHExcJtAS6QeyUQ
					AMAqA43YD6FLMWA+AeAhFQKqKqJhDoSoW5Jm
					LqsUGuGRPAHCHcHEEyDuODKpDKAJFQAkA6DI
					ELNQA+O0BaB4PWASb2cVA2I2LcNoLkc8f4eQ
					HSG2EKC2KEHWqIH+Z/KC3SAK8zHWDoE4T/NS
					AeAo+gPkfIZeP0IItUSCOCH236HMG4VPRK54
					EwDqJ2HaHMODI/KAZOVyJgKqKi1gKi8yAoA6
					DOEVOeA4dRRoM6UQZeU0bgACbsH2HgQeG6VO
					eRIsESDFSMHNRSIMMkYwAWAiBuCZOVBkA4Cw
					DqJCAcAmLKPvPuSWUkQKKFGui2HWGqGUZ/L6
					wSFKEKKC5IpCHssunwI24mI+AeArHMC0DzOU
					A8WABWB2cGPYjqcBUAl4IEf0zYH2hU7+FuE/
					N/F+HYFy3KH7K/TcSOAClgAQAbDfMKA82eDC
					EIJCAivmAY0aocnCSSQArCOCyiHeHEG3O0HM
					f+FMEKJ3FIOCaCrCQCLgz2hEOiz6k+vMMmRO
					b0M6TmKiAiAuAgAyC2DuJCAoA2AaAcA+9wKi
					JOASW+rDLknCTDVUYCf/VmZ/RKHqHgGMFnK8
					HhSTMAwYLdGMI8RQM7XUAiAyDCEPU6AgAkBM
					BlS4ARXEzUSWSgbkTUnIOEYCHcdAHgHsHkGU
					FsNpKoH2HqGsGMKAi2SaHk5KwXKAMggeRtTh
					WMAWBWByM6AevmAeBsCWJAAYAiYxRlRqJAfI
					AOJUIFEsJiw+J9Fs7yhKMPZWOCSsL5PGKEHY
					HLTJWrUeHTYWvHIEKrT5FQCuDxORPiAqBoCI
					JAYwb+h6XGnCLeKRYcAAQRQ1ZMVQGWFvQMTI
					HtZnZqHmX8HWkCJuUiXXSfFOAoMmASAax6BT
					aHFPaMBsCUM6amLKTiugSAXDGrRuU0d+1q1t
					NqSiHyfqsQxHL6OU9Y24FIEGOCHaHKKGHMG7
					OIxhb9AUiiAHXQAJNhNgDTLWAO2eAXXYoU9y
					rGIMW6W4LYSKbo4wHod+L20jdcLah0kAUw3u
					XEJ81kb6T+7wKqh/NlMkuhGqWyUyYGP+vIJa
					MmIK2tZEKCQDR4hUqFBSHGHgHSE0DndxSQH4
					nkYGvJeCAHQUAwDIEXV8TmBKBgM6KuuefIPo
					H+1nflJkIIVBSYLgSebaJ0INfCywH8cJScAM
					caJgtQU0iovxTeUwNkw3fkueXCI62sIGJvb6
					hKf6hSQK9YHcHOE1FEH2nUH1OFd9SXgTaIAs
					PkAiAw6uC4D8fJPWjqA+BaI+ROqXT+3S3wIS
					nDhieFb0XIR/jAZbTesKSUKMOUbUJSJRjER+
					ZeZBheIhjXd+OVZjf+HCQLLvTIE0DiNoHdgJ
					SUdHCNJkAGAcApYyCyD2Ki2efOBKBqPkKmKu
					YsY1MljIj8XE62uiH6k6IU3ubUcVeiXXUCXO
					P2Z+MIIIJNT8Y0cGXWUdk4U0IUXXYc7yd8VQ
					8MJ5iAHViGOCsZd3d7PLiU+ZeEAYLSAEAUAc
					RIBkCIM6bAamCEC6Pk1gJCamiiJKAMJGficP
					LhlmIQSMUxDo1oL3gOW4QqXiKAhS4yGmGEPo
					Tnc6M6jq4mP1amJwnAlyIWZNemZoOkNoJ5YK
					rZRJf8HYE4DkLdkENpGBbVYeACx6jqBcCAKq
					AkA0AWAWCCC6KqAaAnGkihaeb+UUiih8g+Ws
					JLnzdQJ0ZoOSh2k04wwXnRI/ZqVMHvnaMuAK
					NCCMDAcHeZT8fmrDA4IoH+LWvIhFa0JkVKHo
					HmQLiC52E5gEH5mAHzN2hHd/hw8WPoPGfiSA
					AGdOI2m0lgBIBmKqTmRPkiKrmUb+AyBJUqUV
					eGAjq1eil3I++U0iH2HQG8KBK+XgG6kmH7Lo
					HwG0GVEIHtEIHvmeA2AkAwDuFUbI2eAU82AS
					yIJcIrFmUub7WSJ7Q0J4L6HMHAOU9GHiHaE4
					DpoRSQH6eNgPVuSOKkRQBKBmMlaWT+BGBqMn
					JGcGpbrYJLmOfjhsIGP3VqOQH+VOhYHSTOH8
					HsHikuG2GYJ+HoHef4G3sFuFNFq0AnsQAuDm
					FKJAoSNMqkUMJcNik7pObWY9MCJZfoSIOkQE
					HqVuHoKFiDIAE9qfiMHMG3qpmJTcJVXKvNLE
					ARt4JSKiW+I9Kfi+bqMTXAl0mWHuvGJkqPvI
					W+lgKuBSB2M6oSlkC6EMKjFQAQzPHobWPvm+
					nDDnepfpLhwenMKBR5vYHPs9iKHG0qE+DntK
					LdoXkLtVGM0YAOAwBKPkbATmDCESJBoposNc
					NgluINgQkzg1vQIHt7fgOgd+Z6dCOVqYHcE7
					FEH49GKFqmAAKFvxxu+ZgtocAUKuBMPUAIoS
					M2C2ELaIAqlE3uk6ZHjRlISPffvIJtgOOUHs
					4CeTqhxeHeE8DjxntPJBi9zBzC4mAOA0BKKq
					bAWAC/yCALDaAQM0ihSeJLhjwFzoIpDvNqW4
					HuQyHnyoHO0roMNoHYHFy3OHy6xh0N0O6RzE
					lglgBORyAIAqA+AcAgC0EIPlw2/xamcUKQXH
					ycIlFoSESEKAJ4XiHTs9z8LkE4DaLcHeeoH8
					hToZ1f0QJDrV0bSyAeC8EUcHDaASAPT4vOLW
					Mn2EqQUtnznAXJqIJk7yd+StymH3dyVUEuDO
					Lc9GKC/CrCt72xCN1ifaATzMPl1uWACxzZgV
					zccHv4JfxNjql0UwI8ZGkCSbLki3qSGMFbl+
					HDqSFsEpuaHd4BTcfJ210YAHx8AcC33AAJDa
					qWAiigMgM72IIe+4pnyYsP2QQGMOHqGoF+hY
					HV48HgFQEAKBZx5Jxv4ET/4KAH4OAiCv4VGm
					k/ntwINlb0hKMeq6LZvUP8upLv6CHC0qEiC5
					oQHL6T1f5MAOAz5R5UC0ESM70mAKNd3Ngxjm
					SUtWShfkWxdLp+ZChYupiD7CHgHcEcCx7N7R
					5INYJSPHtbkl6cA/eZ6ib3Gnlfk/k5epTflm
					ZLa0QKfwHGGt7CYCEyDSKA258T8T7Vx324dP
					7fYkAzw4AmAlwGyKd5jOY5jBzxa0f4VGGsGR
					46VGFKDuJ+Hi7V9R9QfJ8Z3GAOBKBuKr1uUE
					Ct14AHaKueJRCqR6XW3TjVVQJ2SoH6HiHXGA
					FUD4NoHWwOHyGsGGJkQb+P/cIH5MAMAwBJom
					A59b7gAHYo4mAaAaIAAQCAwGAn+BQMAACAIY
					An6/H+/38/ny/Ho84e73Q9XiqT4/n67XG+ny
					4mrDH4+YZK5ZLZdL5hMZlM5pNZtN5xOZ1O5a
					BISAQKCAMBhCMAEAggGQODCAYaODwuBgIGBJ
					CqO+348HREno7Xw9mGpZA7nM+nw1V9EXw9IY
					+31K3/PLlc7pdbtd7xMgGBAIBQoHwCAgcFQQ
					CaaAgHUL3VIZgYm8XRIHm7Xy92IpYk8XTJG+
					z7a+LzodFo9JpbwAwLDQHgQSDdVAgIB5a/36
					+4ZE38/3y89u/QA/5JcNNw+JxeNx+RLYCAAA
					DwEAAAMAAAABAEAAAAEBAAMAAAABAEAAAAEC
					AAMAAAAEAAAWxAEDAAMAAAABAAUAAAEGAAMA
					AAABAAIAAAERAAQAAAABAAAACAESAAMAAAAB
					AAEAAAEVAAMAAAABAAQAAAEWAAMAAAABAEAA
					AAEXAAQAAAABAAAWAQEcAAMAAAABAAEAAAE9
					AAMAAAABAAIAAAFSAAMAAAABAAEAAAFTAAMA
					AAAEAAAWzIdzAAcAAAfYAAAW1AAAJUgACAAI
					AAgACAABAAEAAQABAAAH2GFwcGwCIAAAbW50
					clJHQiBYWVogB9kAAgAZAAsAGgALYWNzcEFQ
					UEwAAAAAYXBwbAAAAAAAAAAAAAAAAAAAAAAA
					APbWAAEAAAAA0y1hcHBsAAAAAAAAAAAAAAAA
					AAAAAAAAAAAAAAAAAAAAAAAAAAAAAAAAAAAA
					AAAAAAAAAAALZGVzYwAAAQgAAABvZHNjbQAA
					AXgAAAWcY3BydAAABxQAAAA4d3RwdAAAB0wA
					AAAUclhZWgAAB2AAAAAUZ1hZWgAAB3QAAAAU
					YlhZWgAAB4gAAAAUclRSQwAAB5wAAAAOY2hh
					ZAAAB6wAAAAsYlRSQwAAB5wAAAAOZ1RSQwAA
					B5wAAAAOZGVzYwAAAAAAAAAUR2VuZXJpYyBS
					R0IgUHJvZmlsZQAAAAAAAAAAAAAAFEdlbmVy
					aWMgUkdCIFByb2ZpbGUAAAAAAAAAAAAAAAAA
					AAAAAAAAAAAAAAAAAAAAAAAAAAAAAAAAAAAA
					AAAAAAAAAAAAAG1sdWMAAAAAAAAAHwAAAAxz
					a1NLAAAAKAAAAYRkYURLAAAALgAAAaxjYUVT
					AAAAJAAAAdp2aVZOAAAAJAAAAf5wdEJSAAAA
					JgAAAiJ1a1VBAAAAKgAAAkhmckZVAAAAKAAA
					AnJodUhVAAAAKAAAApp6aFRXAAAAFgAAAsJu
					Yk5PAAAAJgAAAthjc0NaAAAAIgAAAv5oZUlM
					AAAAHgAAAyBpdElUAAAAKAAAAz5yb1JPAAAA
					JAAAA2ZkZURFAAAALAAAA4prb0tSAAAAFgAA
					A7ZzdlNFAAAAJgAAAth6aENOAAAAFgAAA8xq
					YUpQAAAAGgAAA+JlbEdSAAAAIgAAA/xwdFBP
					AAAAJgAABB5ubE5MAAAAKAAABERlc0VTAAAA
					JgAABB50aFRIAAAAJAAABGx0clRSAAAAIgAA
					BJBmaUZJAAAAKAAABLJockhSAAAAKAAABNpw
					bFBMAAAALAAABQJydVJVAAAAIgAABS5hckVH
					AAAAJgAABVBlblVTAAAAJgAABXYAVgFhAGUA
					bwBiAGUAYwBuAP0AIABSAEcAQgAgAHAAcgBv
					AGYAaQBsAEcAZQBuAGUAcgBlAGwAIABSAEcA
					QgAtAGIAZQBzAGsAcgBpAHYAZQBsAHMAZQBQ
					AGUAcgBmAGkAbAAgAFIARwBCACAAZwBlAG4A
					6AByAGkAYwBDHqUAdQAgAGgA7ABuAGgAIABS
					AEcAQgAgAEMAaAB1AG4AZwBQAGUAcgBmAGkA
					bAAgAFIARwBCACAARwBlAG4A6QByAGkAYwBv
					BBcEMAQzBDAEOwRMBD0EOAQ5ACAEPwRABD4E
					RAQwBDkEOwAgAFIARwBCAFAAcgBvAGYAaQBs
					ACAAZwDpAG4A6QByAGkAcQB1AGUAIABSAFYA
					QgDBAGwAdABhAGwA4QBuAG8AcwAgAFIARwBC
					ACAAcAByAG8AZgBpAGyQGnUoACAAUgBHAEIA
					IIJyX2ljz4/wAEcAZQBuAGUAcgBpAHMAawAg
					AFIARwBCAC0AcAByAG8AZgBpAGwATwBiAGUA
					YwBuAP0AIABSAEcAQgAgAHAAcgBvAGYAaQBs
					BeQF6AXVBeQF2QXcACAAUgBHAEIAIAXbBdwF
					3AXZAFAAcgBvAGYAaQBsAG8AIABSAEcAQgAg
					AGcAZQBuAGUAcgBpAGMAbwBQAHIAbwBmAGkA
					bAAgAFIARwBCACAAZwBlAG4AZQByAGkAYwBB
					AGwAbABnAGUAbQBlAGkAbgBlAHMAIABSAEcA
					QgAtAFAAcgBvAGYAaQBsx3y8GAAgAFIARwBC
					ACDVBLhc0wzHfGZukBoAIABSAEcAQgAgY8+P
					8GWHTvZOAIIsACAAUgBHAEIAIDDXMO0w1TCh
					MKQw6wOTA7UDvQO5A7oDzAAgA8ADwQO/A8YD
					rwO7ACAAUgBHAEIAUABlAHIAZgBpAGwAIABS
					AEcAQgAgAGcAZQBuAOkAcgBpAGMAbwBBAGwA
					ZwBlAG0AZQBlAG4AIABSAEcAQgAtAHAAcgBv
					AGYAaQBlAGwOQg4bDiMORA4fDiUOTAAgAFIA
					RwBCACAOFw4xDkgOJw5EDhsARwBlAG4AZQBs
					ACAAUgBHAEIAIABQAHIAbwBmAGkAbABpAFkA
					bABlAGkAbgBlAG4AIABSAEcAQgAtAHAAcgBv
					AGYAaQBpAGwAaQBHAGUAbgBlAHIAaQENAGsA
					aQAgAFIARwBCACAAcAByAG8AZgBpAGwAVQBu
					AGkAdwBlAHIAcwBhAGwAbgB5ACAAcAByAG8A
					ZgBpAGwAIABSAEcAQgQeBDEESQQ4BDkAIAQ/
					BEAEPgREBDgEOwRMACAAUgBHAEIGRQZEBkEA
					IAYqBjkGMQZKBkEAIABSAEcAQgAgBicGRAY5
					BicGRQBHAGUAbgBlAHIAaQBjACAAUgBHAEIA
					IABQAHIAbwBmAGkAbABldGV4dAAAAABDb3B5
					cmlnaHQgMjAwNyBBcHBsZSBJbmMuLCBhbGwg
					cmlnaHRzIHJlc2VydmVkLgBYWVogAAAAAAAA
					81IAAQAAAAEWz1hZWiAAAAAAAAB0TQAAPe4A
					AAPQWFlaIAAAAAAAAFp1AACscwAAFzRYWVog
					AAAAAAAAKBoAABWfAAC4NmN1cnYAAAAAAAAA
					AQHNAABzZjMyAAAAAAABDEIAAAXe///zJgAA
					B5IAAP2R///7ov///aMAAAPcAADAbIAAIFA4
					JBYNB4RCYVC4ZDYdD4hEYOAwKCwcEA8PCQCw
					wLhqBgUGA7BH293U5nq6WkyXe4WIuX6+nm8I
					lNZtN4MBwYGQ+HRyeUeExGRCiCgO/wAAwG/Q
					ABAFBn9SAA+34AwA9nyAQA7m+wFo4mOhje+X
					k5G9OLRaYGGRcYDoHhqc0WDge/gABwDUqtBX
					+/38/gCAQFT4O/35fX0AAEAXk9ae42SkT05m
					gnEPasxDRCPUIoA0KicXweCsPgIEAr7fn8Aw
					E+n7T37TILSoEBgHdsHUcBfdRgXk+QIAXI0V
					gn3AxT8YszywAGRaZj6Ih4a0EDgRdr9Wn8+6
					i9H3i3c5W61Hi5Fup3w8XA2cEBAMBwaHBCEA
					+RysDgqJheEATdgC4IAMEpB5nsp5vGQTRCHM
					aJKj65iagQB4RBUFgoleaoKAYfgAN4qZ+rsd
					p3HyebjjsLB4nKYhbJsBwMhwIoQh4RhVgmCY
					EgeArWIGfp/nceYCgCapZiqGB7HebRowehwR
					iEThgA+EoYB+watNSAB0nUex4GuWglhEmJ5n
					e5YBgMBwJBQJZYmyDALgaCjFQ+f5+tYcRums
					ZBuF4LwcyUhKQAyEAWigWhvgfDSpIEeJ6OCb
					BcjCHZ6naaRjT6ggFAkFQahSJBRmVQzDoEvp
					5HsAoBGkWAnBGfR6HKs9KoECgTCyOAShsORH
					gQAx+L+fynHGbxnmEbxhDMH9XoUEIdkoXQOB
					IG4igKAi7HufKnm4ZZJjwdZslERNjgADwZkM
					VQQBQIIqgCAq/nxUgBG0ZJBDElpaE/b6EAgD
					ojC0E4ckIUoEgWph/MSABwm0YZYHCZY7Cjb4
					RBwTpkA2EQUhuwK/wJUpsl+MAby0a5lXsg4E
					AcEgXhSIZSmgB2AgAv6BHIcpuGeb5gi8GVvh
					AHROmYDYOBSGYAgGvp6HtAJsmAMIZHueJtGf
					kScgYEAVBOIRSmq6y/KQwZ0HHJBumOMAYW+D
					oYkYW2JhyJIA14e7vgEbplDwKR5nUYZX6ggs
					3B0JgSBwRRZgSAztK0ABym+ZJdHGZw5CPb4K
					BAMhBg8FovD4AlpV4wZyGuXJRnQbRCi9vKCA
					wEw7k5n4ljG2gAH4fitHEaZRkOdZvk0PVvgQ
					BgThqEQbE2ZQGAYv7AsGeB1qYbhmCmDKYncd
					FvgEAYFghZxaneB4JLz6bAnmeamG+ZY2B2e5
					5mrSmoA8GBTnACoLguD7A5c2LFJObRmHKao0
					Brb4NgqEqMcCoGgUg4cwXk1IAR1pYHEOIaAW
					APukIGAsCIPApM/ECK0BgDTtF2KmwQdw5xqj
					IHONwOwRi/PmJsYEAwCQMAnESLgCQEwXg+d2
					QIv6Hx8D0NYOYbolA4DxHUK4SMEiDAWA+IMW
					gFQNg5CWe8gw+juAAHqPA2I8h2CvEiPUeIwB
					Tj7H0OkcMOB+gFAMBcEACgHg/CsA8DAUg5AL
					AYAWMypUOADSqaov5g3zFIS0N4ao6RwB3CIP
					0fg73oxGAyCISw0QIOmBcAYwg/gBPFMEAKMB
					TCSlWhyQIAjW1egAAKAkpgBFSj/MC/Mwo+ni
					ySMWbJDZdh4jrHjCEboZwWSGhDBIwQFgNiFF
					0AwCgMQhgKAUYRocHiDj9lUQNoaiCBvzKYAE
					fI+CkSmL8mQxaoZoEEYGYOLA8B3jnHEGcFUh
					pERGAAAsB4RAwPaDII4BEagIyjIEAMpyAUOF
					8n1IYuxJSBD5HsTMeo8xeChAiBkKIbwEgKL8
					ACZhhCDD/k4dkAU4R3jpHEGkFZsZxzqIIAgB
					YNQmMABwFE94JQagCAIBIDU3pDjoH0Pl5a7B
					kivHuPQZAsSCAZBCKoeYDwIAOAYf+bpBC+yW
					NyPsgQ8pxDuHUOMNgLTYjuHNSBqB7wSA1AqB
					wRoyo5AFQDKo2VSTASXKTDiKb3x31QHKG0Fg
					/h+0fqwvY94JgbgUA0IsZACgEtDKSX0gUqrB
					EIH4YMeY9B3jvHWOYNgKq5DwkTXVY4BQDq1A
					oBkRIyQFgGAIhwxcyqJEIKibwelih3DrHOGs
					Epfh6Dusot+ywJQbgTAuIavsUD/uFMKap4wA
					h+D7KYPAeAvhRjxHaJJ0dsWRWzBwBIC4hRjg
					KstPcgcqEOW+MWbAgSBGujsHOGcD1zIJWWWc
					BECwhRkAJAOUc7RUrCFIoiPAeL6B4DuD4Du8
					lIIzAkBtegQgyQERmMUgEvseAAj4H0YmjIgQ
					hUzGqL+/dlJTAdBZOwMYlqtA3uCOgbY9R5Cl
					DsPofAz0V4TxQWkgIAAPAQAAAwAAAAEAIAAA
					AQEAAwAAAAEAIAAAAQIAAwAAAAQAACYCAQMA
					AwAAAAEABQAAAQYAAwAAAAEAAgAAAREABAAA
					AAEAAB6sARIAAwAAAAEAAQAAARUAAwAAAAEA
					BAAAARYAAwAAAAEAIAAAARcABAAAAAEAAAac
					ARwAAwAAAAEAAQAAAT0AAwAAAAEAAgAAAVIA
					AwAAAAEAAQAAAVMAAwAAAAQAACYKh3MABwAA
					B9gAACYSAAAwmAAIAAgACAAIAAEAAQABAAEA
					AAfYYXBwbAIgAABtbnRyUkdCIFhZWiAH2QAC
					ABkACwAaAAthY3NwQVBQTAAAAABhcHBsAAAA
					AAAAAAAAAAAAAAAAAAAA9tYAAQAAAADTLWFw
					cGwAAAAAAAAAAAAAAAAAAAAAAAAAAAAAAAAA
					AAAAAAAAAAAAAAAAAAAAAAAAAAAAAAtkZXNj
					AAABCAAAAG9kc2NtAAABeAAABZxjcHJ0AAAH
					FAAAADh3dHB0AAAHTAAAABRyWFlaAAAHYAAA
					ABRnWFlaAAAHdAAAABRiWFlaAAAHiAAAABRy
					VFJDAAAHnAAAAA5jaGFkAAAHrAAAACxiVFJD
					AAAHnAAAAA5nVFJDAAAHnAAAAA5kZXNjAAAA
					AAAAABRHZW5lcmljIFJHQiBQcm9maWxlAAAA
					AAAAAAAAAAAUR2VuZXJpYyBSR0IgUHJvZmls
					ZQAAAAAAAAAAAAAAAAAAAAAAAAAAAAAAAAAA
					AAAAAAAAAAAAAAAAAAAAAAAAAAAAAAAAbWx1
					YwAAAAAAAAAfAAAADHNrU0sAAAAoAAABhGRh
					REsAAAAuAAABrGNhRVMAAAAkAAAB2nZpVk4A
					AAAkAAAB/nB0QlIAAAAmAAACInVrVUEAAAAq
					AAACSGZyRlUAAAAoAAACcmh1SFUAAAAoAAAC
					mnpoVFcAAAAWAAACwm5iTk8AAAAmAAAC2GNz
					Q1oAAAAiAAAC/mhlSUwAAAAeAAADIGl0SVQA
					AAAoAAADPnJvUk8AAAAkAAADZmRlREUAAAAs
					AAADimtvS1IAAAAWAAADtnN2U0UAAAAmAAAC
					2HpoQ04AAAAWAAADzGphSlAAAAAaAAAD4mVs
					R1IAAAAiAAAD/HB0UE8AAAAmAAAEHm5sTkwA
					AAAoAAAERGVzRVMAAAAmAAAEHnRoVEgAAAAk
					AAAEbHRyVFIAAAAiAAAEkGZpRkkAAAAoAAAE
					smhySFIAAAAoAAAE2nBsUEwAAAAsAAAFAnJ1
					UlUAAAAiAAAFLmFyRUcAAAAmAAAFUGVuVVMA
					AAAmAAAFdgBWAWEAZQBvAGIAZQBjAG4A/QAg
					AFIARwBCACAAcAByAG8AZgBpAGwARwBlAG4A
					ZQByAGUAbAAgAFIARwBCAC0AYgBlAHMAawBy
					AGkAdgBlAGwAcwBlAFAAZQByAGYAaQBsACAA
					UgBHAEIAIABnAGUAbgDoAHIAaQBjAEMepQB1
					ACAAaADsAG4AaAAgAFIARwBCACAAQwBoAHUA
					bgBnAFAAZQByAGYAaQBsACAAUgBHAEIAIABH
					AGUAbgDpAHIAaQBjAG8EFwQwBDMEMAQ7BEwE
					PQQ4BDkAIAQ/BEAEPgREBDAEOQQ7ACAAUgBH
					AEIAUAByAG8AZgBpAGwAIABnAOkAbgDpAHIA
					aQBxAHUAZQAgAFIAVgBCAMEAbAB0AGEAbADh
					AG4AbwBzACAAUgBHAEIAIABwAHIAbwBmAGkA
					bJAadSgAIABSAEcAQgAggnJfaWPPj/AARwBl
					AG4AZQByAGkAcwBrACAAUgBHAEIALQBwAHIA
					bwBmAGkAbABPAGIAZQBjAG4A/QAgAFIARwBC
					ACAAcAByAG8AZgBpAGwF5AXoBdUF5AXZBdwA
					IABSAEcAQgAgBdsF3AXcBdkAUAByAG8AZgBp
					AGwAbwAgAFIARwBCACAAZwBlAG4AZQByAGkA
					YwBvAFAAcgBvAGYAaQBsACAAUgBHAEIAIABn
					AGUAbgBlAHIAaQBjAEEAbABsAGcAZQBtAGUA
					aQBuAGUAcwAgAFIARwBCAC0AUAByAG8AZgBp
					AGzHfLwYACAAUgBHAEIAINUEuFzTDMd8Zm6Q
					GgAgAFIARwBCACBjz4/wZYdO9k4AgiwAIABS
					AEcAQgAgMNcw7TDVMKEwpDDrA5MDtQO9A7kD
					ugPMACADwAPBA78DxgOvA7sAIABSAEcAQgBQ
					AGUAcgBmAGkAbAAgAFIARwBCACAAZwBlAG4A
					6QByAGkAYwBvAEEAbABnAGUAbQBlAGUAbgAg
					AFIARwBCAC0AcAByAG8AZgBpAGUAbA5CDhsO
					Iw5EDh8OJQ5MACAAUgBHAEIAIA4XDjEOSA4n
					DkQOGwBHAGUAbgBlAGwAIABSAEcAQgAgAFAA
					cgBvAGYAaQBsAGkAWQBsAGUAaQBuAGUAbgAg
					AFIARwBCAC0AcAByAG8AZgBpAGkAbABpAEcA
					ZQBuAGUAcgBpAQ0AawBpACAAUgBHAEIAIABw
					AHIAbwBmAGkAbABVAG4AaQB3AGUAcgBzAGEA
					bABuAHkAIABwAHIAbwBmAGkAbAAgAFIARwBC
					BB4EMQRJBDgEOQAgBD8EQAQ+BEQEOAQ7BEwA
					IABSAEcAQgZFBkQGQQAgBioGOQYxBkoGQQAg
					AFIARwBCACAGJwZEBjkGJwZFAEcAZQBuAGUA
					cgBpAGMAIABSAEcAQgAgAFAAcgBvAGYAaQBs
					AGV0ZXh0AAAAAENvcHlyaWdodCAyMDA3IEFw
					cGxlIEluYy4sIGFsbCByaWdodHMgcmVzZXJ2
					ZWQuAFhZWiAAAAAAAADzUgABAAAAARbPWFla
					IAAAAAAAAHRNAAA97gAAA9BYWVogAAAAAAAA
					WnUAAKxzAAAXNFhZWiAAAAAAAAAoGgAAFZ8A
					ALg2Y3VydgAAAAAAAAABAc0AAHNmMzIAAAAA
					AAEMQgAABd7///MmAAAHkgAA/ZH///ui///9
					owAAA9wAAMBsgAAgUDgkFgQBAYFA4NDYgAAC
					iD6ejncb/fj5e0GjUbjkaAIEAwXFJSMYeF5T
					MgMCQdEkIAQDervdLgcjUWamc7TUyTfz8ezz
					jtBgYBAQFBAjHp9SwlGxbML9fT4ADxdTZaz+
					fz9fgNCokFgJlQCb7RWa3bK8PBZfr7ejxoUb
					CwoLJtGJJQiSd7nbLhbDBQ5rebrZzDAFZfoJ
					CQnF4mHh6SoZEQ3GDVYKSRriZqOOlvoYEBAL
					F5KUDJBoUEwmZyzM5IerrZa+oQGBogFIzJyi
					Yz9fr5frOWBaFz8fDrc1CA4MEYtGJLULMejt
					bbTai8Mg5gVrzkCEg6RKvDQlJBQZy3NBJejq
					Y644wNEwyF5FT7MeDqaDEbTENg/gT/f/ZAAP
					hkPxSg4EoqC0aJfDSJ56HWYpZKEAQCAgCoUh
					6TRmgIAoHAaaxhDKHB9nwcZsqEhAGAgFIdk8
					aACASCAKGuYQxhmfZ7xG/wKhANRHBAFQyjid
					Rwl8X5xmwRIwKydRxIIogGAiDISDgSoNBGJw
					snUcZhF8cRqDsIqBKw/yIAeCwOBMQZZgkDQc
					hsep4G4dB5HYZ5dP6fZ9AWCIXB+BzEhKAB/n
					uAB9Hy4R2HMXpUnWcJHjQgUQzEAYIg0CYMjG
					RMXh4KADASC4GACh4AHyfB1Hweh5m4aIGgeE
					4agOAwBgEfx/gSAB1HIWhTHWchHjFR58v8gi
					Eg0E4DAMEIWgAogCH4fRyGvO5yGyCwNjuVQJ
					AuIgmn+fx7P6AIEACdhzlqUx2nQSNfAAi9g3
					bZQAxcCYLjqUoIgkHwlVmfB/gDcAAnadRZFC
					d52EsM13YQg4EgeCYKjmU4HggIAkoFQTdP6c
					pwjgG2E47hQHAgCY2lEBwHB+J57HqaRknadZ
					DCbj2YoOo0MhEGitHMbVuHmdSAgADwEAAAMA
					AAABABAAAAEBAAMAAAABABAAAAECAAMAAAAE
					AAAxUgEDAAMAAAABAAUAAAEGAAMAAAABAAIA
					AAERAAQAAAABAAAt6gESAAMAAAABAAEAAAEV
					AAMAAAABAAQAAAEWAAMAAAABABAAAAEXAAQA
					AAABAAACrgEcAAMAAAABAAEAAAE9AAMAAAAB
					AAIAAAFSAAMAAAABAAEAAAFTAAMAAAAEAAAx
					WodzAAcAAAfYAAAxYgAAAAAACAAIAAgACAAB
					AAEAAQABAAAH2GFwcGwCIAAAbW50clJHQiBY
					WVogB9kAAgAZAAsAGgALYWNzcEFQUEwAAAAA
					YXBwbAAAAAAAAAAAAAAAAAAAAAAAAPbWAAEA
					AAAA0y1hcHBsAAAAAAAAAAAAAAAAAAAAAAAA
					AAAAAAAAAAAAAAAAAAAAAAAAAAAAAAAAAAAA
					AAALZGVzYwAAAQgAAABvZHNjbQAAAXgAAAWc
					Y3BydAAABxQAAAA4d3RwdAAAB0wAAAAUclhZ
					WgAAB2AAAAAUZ1hZWgAAB3QAAAAUYlhZWgAA
					B4gAAAAUclRSQwAAB5wAAAAOY2hhZAAAB6wA
					AAAsYlRSQwAAB5wAAAAOZ1RSQwAAB5wAAAAO
					ZGVzYwAAAAAAAAAUR2VuZXJpYyBSR0IgUHJv
					ZmlsZQAAAAAAAAAAAAAAFEdlbmVyaWMgUkdC
					IFByb2ZpbGUAAAAAAAAAAAAAAAAAAAAAAAAA
					AAAAAAAAAAAAAAAAAAAAAAAAAAAAAAAAAAAA
					AAAAAG1sdWMAAAAAAAAAHwAAAAxza1NLAAAA
					KAAAAYRkYURLAAAALgAAAaxjYUVTAAAAJAAA
					Adp2aVZOAAAAJAAAAf5wdEJSAAAAJgAAAiJ1
					a1VBAAAAKgAAAkhmckZVAAAAKAAAAnJodUhV
					AAAAKAAAApp6aFRXAAAAFgAAAsJuYk5PAAAA
					JgAAAthjc0NaAAAAIgAAAv5oZUlMAAAAHgAA
					AyBpdElUAAAAKAAAAz5yb1JPAAAAJAAAA2Zk
					ZURFAAAALAAAA4prb0tSAAAAFgAAA7ZzdlNF
					AAAAJgAAAth6aENOAAAAFgAAA8xqYUpQAAAA
					GgAAA+JlbEdSAAAAIgAAA/xwdFBPAAAAJgAA
					BB5ubE5MAAAAKAAABERlc0VTAAAAJgAABB50
					aFRIAAAAJAAABGx0clRSAAAAIgAABJBmaUZJ
					AAAAKAAABLJockhSAAAAKAAABNpwbFBMAAAA
					LAAABQJydVJVAAAAIgAABS5hckVHAAAAJgAA
					BVBlblVTAAAAJgAABXYAVgFhAGUAbwBiAGUA
					YwBuAP0AIABSAEcAQgAgAHAAcgBvAGYAaQBs
					AEcAZQBuAGUAcgBlAGwAIABSAEcAQgAtAGIA
					ZQBzAGsAcgBpAHYAZQBsAHMAZQBQAGUAcgBm
					AGkAbAAgAFIARwBCACAAZwBlAG4A6AByAGkA
					YwBDHqUAdQAgAGgA7ABuAGgAIABSAEcAQgAg
					AEMAaAB1AG4AZwBQAGUAcgBmAGkAbAAgAFIA
					RwBCACAARwBlAG4A6QByAGkAYwBvBBcEMAQz
					BDAEOwRMBD0EOAQ5ACAEPwRABD4ERAQwBDkE
					OwAgAFIARwBCAFAAcgBvAGYAaQBsACAAZwDp
					AG4A6QByAGkAcQB1AGUAIABSAFYAQgDBAGwA
					dABhAGwA4QBuAG8AcwAgAFIARwBCACAAcABy
					AG8AZgBpAGyQGnUoACAAUgBHAEIAIIJyX2lj
					z4/wAEcAZQBuAGUAcgBpAHMAawAgAFIARwBC
					AC0AcAByAG8AZgBpAGwATwBiAGUAYwBuAP0A
					IABSAEcAQgAgAHAAcgBvAGYAaQBsBeQF6AXV
					BeQF2QXcACAAUgBHAEIAIAXbBdwF3AXZAFAA
					cgBvAGYAaQBsAG8AIABSAEcAQgAgAGcAZQBu
					AGUAcgBpAGMAbwBQAHIAbwBmAGkAbAAgAFIA
					RwBCACAAZwBlAG4AZQByAGkAYwBBAGwAbABn
					AGUAbQBlAGkAbgBlAHMAIABSAEcAQgAtAFAA
					cgBvAGYAaQBsx3y8GAAgAFIARwBCACDVBLhc
					0wzHfGZukBoAIABSAEcAQgAgY8+P8GWHTvZO
					AIIsACAAUgBHAEIAIDDXMO0w1TChMKQw6wOT
					A7UDvQO5A7oDzAAgA8ADwQO/A8YDrwO7ACAA
					UgBHAEIAUABlAHIAZgBpAGwAIABSAEcAQgAg
					AGcAZQBuAOkAcgBpAGMAbwBBAGwAZwBlAG0A
					ZQBlAG4AIABSAEcAQgAtAHAAcgBvAGYAaQBl
					AGwOQg4bDiMORA4fDiUOTAAgAFIARwBCACAO
					Fw4xDkgOJw5EDhsARwBlAG4AZQBsACAAUgBH
					AEIAIABQAHIAbwBmAGkAbABpAFkAbABlAGkA
					bgBlAG4AIABSAEcAQgAtAHAAcgBvAGYAaQBp
					AGwAaQBHAGUAbgBlAHIAaQENAGsAaQAgAFIA
					RwBCACAAcAByAG8AZgBpAGwAVQBuAGkAdwBl
					AHIAcwBhAGwAbgB5ACAAcAByAG8AZgBpAGwA
					IABSAEcAQgQeBDEESQQ4BDkAIAQ/BEAEPgRE
					BDgEOwRMACAAUgBHAEIGRQZEBkEAIAYqBjkG
					MQZKBkEAIABSAEcAQgAgBicGRAY5BicGRQBH
					AGUAbgBlAHIAaQBjACAAUgBHAEIAIABQAHIA
					bwBmAGkAbABldGV4dAAAAABDb3B5cmlnaHQg
					MjAwNyBBcHBsZSBJbmMuLCBhbGwgcmlnaHRz
					IHJlc2VydmVkLgBYWVogAAAAAAAA81IAAQAA
					AAEWz1hZWiAAAAAAAAB0TQAAPe4AAAPQWFla
					IAAAAAAAAFp1AACscwAAFzRYWVogAAAAAAAA
					KBoAABWfAAC4NmN1cnYAAAAAAAAAAQHNAABz
					ZjMyAAAAAAABDEIAAAXe///zJgAAB5IAAP2R
					///7ov///aMAAAPcAADAbA==
					</data>
		<key>ModificationDate</key>
		<real>759492066.43033195</real>
		<key>Name</key>
		<string>Spotlight Search Prompt</string>
		<key>Triggers</key>
		<array/>
		<key>UID</key>
		<string>0BC9A4AD-D089-4160-B5E5-ECF032644797</string>
	</dict>
</array>
</plist>
