{
	"CreationDate": 519848269.092785,
	"UID": "664EFA88-92C3-4307-A0E0-B9679D47D565",
	"Name": "1Password",
	"Triggers": [],
	"ModificationDate": 654717267.128474,
	"Actions": [
		{
			"MacroActionType": "SetVariableToKeychainPassword",
			"PasswordAccount": "%UserLoginID%",
			"Variable": "Password",
			"PasswordName": "1Password"
		},
		{
			"MacroActionType": "SetVariableToText",
			"Variable": "Password",
			"Text": "%Variable%Password%"
		},
		{
			"MacroActionType": "SetClipboardToText",
			"JustDisplay": false,
			"Text": "%Variable%Password%"
		},
		{
			"MacroActionType": "SimulateKeystroke",
			"Modifiers": 256,
			"TargetApplication": {},
			"ReleaseAll": false,
			"TargetingType": "Front",
			"KeyCode": 9
		},
		{
			"MacroActionType": "SimulateKeystroke",
			"Modifiers": 0,
			"TargetApplication": {},
			"ReleaseAll": false,
			"TargetingType": "Front",
			"KeyCode": 36
		},
		{
			"MacroActionType": "SetVariableToText",
			"Variable": "Password",
			"Text": "%Delete%"
		}
	]
}